kestra_ion/__init__.py
kestra_ion/reader.py
tests/__init__.py
tests/test_reader.py
kestra_ion-0.0.2.dist-info/LICENSE
kestra_ion-0.0.2.dist-info/METADATA
kestra_ion-0.0.2.dist-info/WHEEL
kestra_ion-0.0.2.dist-info/top_level.txt
kestra_ion-0.0.2.dist-info/RECORD
