Metadata-Version: 2.1
Name: kestra-ion
Version: 0.0.2
Summary: A simple package to read Ion data into a list of dictionaries suitable for use in dataframes.
Home-page: https://github.com/anna-geller/kestra-ion
Author: Anna Geller
Author-email: hello@kestra.io
License: LICENSE.txt
Classifier: Programming Language :: Python :: 3
Classifier: Programming Language :: Python :: 3.8
Classifier: Programming Language :: Python :: 3.9
Classifier: Programming Language :: Python :: 3.10
Classifier: Programming Language :: Python :: 3.11
License-File: LICENSE
Requires-Dist: amazon.ion
Requires-Dist: python-dateutil
Provides-Extra: test
Requires-Dist: pytest ; extra == 'test'
